{"cameraMode":{"drawMode":0,"name":"Shaded","section":"Shading Mode"},"sceneLighting":false,"audioPlay":false,"sceneViewState":{"showFog":true,"showMaterialUpdate":false,"showSkybox":false,"showFlares":true,"showImageEffects":true,"showParticleSystems":true},"in2DMode":false,"pivot":{"x":423.08258056640627,"y":55.131858825683597,"z":-118.93863677978516},"rotation":{"x":-0.20713359117507935,"y":0.7641022205352783,"z":-0.2873484790325165,"w":-0.5404431819915772},"size":0.9413886070251465,"orthographic":false}